govee_api_laggat/__init__.py
govee_api_laggat/__version__.py
govee_api_laggat/api.py
govee_api_laggat/ble.py
govee_api_laggat/govee_api_laggat.py
govee_api_laggat/govee_dtos.py
govee_api_laggat/learning_storage.py
tests/__init__.py
tests/mockdata.py
tests/test_pytest.py
govee_api_laggat-0.2.2.dist-info/LICENSE
govee_api_laggat-0.2.2.dist-info/METADATA
govee_api_laggat-0.2.2.dist-info/WHEEL
govee_api_laggat-0.2.2.dist-info/top_level.txt
govee_api_laggat-0.2.2.dist-info/RECORD
