Metadata-Version: 2.1
Name: govee-api-laggat
Version: 0.2.2
Summary: Implementation of the govee API to control LED strips and bulbs.
Home-page: https://github.com/LaggAt/python-govee-api
Author: Florian Lagg @LaggAt
Author-email: florian.lagg@gmail.com
License: UNKNOWN
Platform: UNKNOWN
Classifier: Programming Language :: Python :: 3
Classifier: License :: OSI Approved :: MIT License
Classifier: Operating System :: OS Independent
Requires-Python: >=3.7
Requires-Dist: aiohttp (>=3.7.1)
Requires-Dist: bios (>=0.1.2)
Requires-Dist: certifi (>=2021.10.8)
Requires-Dist: dacite (>=1.6.0)
Requires-Dist: events (>=0.3)
Requires-Dist: pexpect (>=4.8.0)
Requires-Dist: pygatt (>=4.0.5)
